MANIFEST.in
README.rst
setup.py
terrabot/__init__.py
terrabot/bot.py
terrabot/client.py
terrabot.egg-info/PKG-INFO
terrabot.egg-info/SOURCES.txt
terrabot.egg-info/dependency_links.txt
terrabot.egg-info/requires.txt
terrabot.egg-info/top_level.txt
terrabot/data/__init__.py
terrabot/data/item.py
terrabot/data/player.py
terrabot/data/tile.py
terrabot/data/world.py
terrabot/events/__init__.py
terrabot/events/eventmanager.py
terrabot/events/events.py
terrabot/packets/Packet39.py
terrabot/packets/__init__.py
terrabot/packets/packet.py
terrabot/packets/packet1.py
terrabot/packets/packet10.py
terrabot/packets/packet14.py
terrabot/packets/packet15.py
terrabot/packets/packet16.py
terrabot/packets/packet17.py
terrabot/packets/packet19.py
terrabot/packets/packet1B.py
terrabot/packets/packet1E.py
terrabot/packets/packet2.py
terrabot/packets/packet2a.py
terrabot/packets/packet3.py
terrabot/packets/packet31.py
terrabot/packets/packet32.py
terrabot/packets/packet39.py
terrabot/packets/packet3D.py
terrabot/packets/packet4.py
terrabot/packets/packet41.py
terrabot/packets/packet5.py
terrabot/packets/packet52.py
terrabot/packets/packet53.py
terrabot/packets/packet6.py
terrabot/packets/packet7.py
terrabot/packets/packet8.py
terrabot/packets/packet9.py
terrabot/packets/packetA.py
terrabot/packets/packetB.py
terrabot/packets/packetC.py
terrabot/packets/packetD.py
terrabot/packets/packetE.py
terrabot/util/__init__.py
terrabot/util/streamer.py
terrabot/util/tileutil.py
terrabot/util/worlddrawer.py