Metadata-Version: 1.1
Name: terrabot
Version: 1.0.2
Summary: A library for making Terraria bots in a event driven manner
Home-page: https://github.com/flammified/terrabot
Author: Alexander Freeman
Author-email: alexander.freeman.nl@gmail.com
License: MIT
Keywords: terraria bot event driven library
Platform: UNKNOWN
Classifier: Development Status :: 3 - Alpha
Classifier: Intended Audience :: Developers
Classifier: Topic :: Software Development :: Libraries
Classifier: License :: OSI Approved :: MIT License
Classifier: Programming Language :: Python :: 3
